tm1637.py
raspberrypi_python_tm1637-1.3.0.dist-info/LICENSE.txt
raspberrypi_python_tm1637-1.3.0.dist-info/METADATA
raspberrypi_python_tm1637-1.3.0.dist-info/WHEEL
raspberrypi_python_tm1637-1.3.0.dist-info/top_level.txt
raspberrypi_python_tm1637-1.3.0.dist-info/RECORD
