Metadata-Version: 2.1
Name: raspberrypi-python-tm1637
Version: 1.3.0
Summary: Raspberry Pi Python port from MicroPython library for TM1637 LED driver.
Home-page: https://github.com/lawerencem/raspberrypi-python-tm1637
Author: Mike Causer
Author-email: mcauser@gmail.com
Maintainer: Lawerence E. Mize, Jr.
Maintainer-email: lawerencem@gmail.com
License: MIT
Keywords: tm1637 raspberry pi seven segment led python
Platform: UNKNOWN
Classifier: Development Status :: 5 - Production/Stable
Classifier: Programming Language :: Python :: 3
Classifier: License :: OSI Approved :: MIT License
